SmithWagnerCV/.DS_Store
SmithWagnerCV/Methods.py
SmithWagnerCV/__init__.py
smithwagnercv-0.1.0.dist-info/METADATA
smithwagnercv-0.1.0.dist-info/WHEEL
smithwagnercv-0.1.0.dist-info/licenses/LICENSE
smithwagnercv-0.1.0.dist-info/RECORD
